AUTHORS.rst
CONTRIBUTING.rst
HISTORY.rst
LICENSE
MANIFEST.in
README.rst
setup.cfg
setup.py
django_nupages.egg-info/PKG-INFO
django_nupages.egg-info/SOURCES.txt
django_nupages.egg-info/dependency_links.txt
django_nupages.egg-info/not-zip-safe
django_nupages.egg-info/requires.txt
django_nupages.egg-info/top_level.txt
nupages/__init__.py
nupages/admin.py
nupages/managers.py
nupages/middleware.py
nupages/models.py
nupages/urls.py
nupages/views.py
nupages/fixtures/__init__.py
nupages/migrations/0001_initial.py
nupages/migrations/__init__.py
nupages/static/js/nupages.js
nupages/templates/base.html
nupages/templates/nupages/base.html
nupages/templates/nupages/index.html
nupages/templates/nupages/page_detail.html
nupages/templates/nupages/page_list.html
nupages/templates/nupages/test-page-custom-template.html