Metadata-Version: 1.1
Name: django-nupages
Version: 0.1.7
Summary: Pages application for django projects
Home-page: https://github.com/goldhand/django-nupages
Author: Will Farley
Author-email: will@django.nu
License: BSD
Keywords: django-nupages
Platform: UNKNOWN
Classifier: Development Status :: 2 - Pre-Alpha
Classifier: Framework :: Django
Classifier: Intended Audience :: Developers
Classifier: License :: OSI Approved :: BSD License
Classifier: Natural Language :: English
Classifier: Programming Language :: Python :: 2
Classifier: Programming Language :: Python :: 2.6
Classifier: Programming Language :: Python :: 2.7
Classifier: Programming Language :: Python :: 3
Classifier: Programming Language :: Python :: 3.3
